tai/__init__.py
tai/cli.py
lfg_llama-3.0.1.dist-info/METADATA
lfg_llama-3.0.1.dist-info/WHEEL
lfg_llama-3.0.1.dist-info/entry_points.txt
lfg_llama-3.0.1.dist-info/top_level.txt
lfg_llama-3.0.1.dist-info/RECORD
