Metadata-Version: 2.1
Name: lfg-llama
Version: 3.0.1
Summary: TAI [Terminal AI], a terminal AI assistant
Author: Bjarne Oeverli
Author-email: bjarneocodes@gmail.com
Requires-Dist: openai
